<?xml version="1.0" encoding="UTF-8"?>
<?xml-stylesheet href="stylesheets/modshtml.xsl" type="text/xsl" ?>
<mods  version="3.1" xmlns="http://www.loc.gov/mods/v3" ID="contata94">
<recordInfo>
<recordCreationDate>2006-11-17</recordCreationDate>
<recordChangeDate>2009-09-24</recordChangeDate>
</recordInfo>
<titleInfo>
<title>Contata 1994 Program Book</title>
</titleInfo>
<language>
<languageTerm type="code" authority="iso639-2b">eng</languageTerm>
</language>
<physicalDescription>
<form authority="marcform">print</form>
</physicalDescription>
<abstract>Program book with songs for Contata 1994, the New York
City area filk convention</abstract>
<originInfo>
<place>
  <placeTerm type="text">New Jersey</placeTerm>
</place>
<publisher></publisher>
<dateIssued>1994</dateIssued>
</originInfo>
<name type="personal">
<namePart>Grumer, Avram</namePart>
<role>
<roleTerm>editor</roleTerm>
</role>
</name>
<relatedItem type="constituent">
<titleInfo>
<title>Please Push That Button</title>
</titleInfo>
<name type="personal">
<namePart>Levine, Rennie</namePart>
<role>
<roleTerm>lyricist</roleTerm>
</role>
</name>
<relatedItem type="preceding">
<titleInfo>
<title>Don't Push That Button</title>
</titleInfo>
<name type="personal">
<namePart>Elms, Duane</namePart>
<role>
<roleTerm>composer</roleTerm>
</role>
</name>
<note>Tune used or parodied</note>
</relatedItem>

</relatedItem>
<relatedItem type="constituent">
<titleInfo>
<title>Edward K.</title>
</titleInfo>
<name type="personal">
<namePart>Levine, Rennie</namePart>
<role>
<roleTerm>lyricist</roleTerm>
</role>
</name>
<name type="personal">
<namePart>Cochrane, Susan</namePart>
<role>
<roleTerm>lyricist</roleTerm>
</role>
</name>
<relatedItem type="preceding">
<titleInfo>
<title>Edward</title>
</titleInfo>
<name type="personal">
<namePart>Mar, Kathy</namePart>
<role>
<roleTerm>composer</roleTerm>
</role>
</name>
<note>Tune used or parodied</note>
</relatedItem>

</relatedItem>
<relatedItem type="constituent">
<titleInfo>
<title>Nick the Knife</title>
</titleInfo>
<name type="personal">
<namePart>Grumer, Avram</namePart>
<role>
<roleTerm>lyricist</roleTerm>
</role>
</name>
<relatedItem type="preceding">
<titleInfo>
<title>Mack the Knife</title>
</titleInfo>
<name type="personal">
<namePart>Weill, Kurt</namePart>
<role>
<roleTerm>composer</roleTerm>
</role>
</name>
<note>Tune used or parodied</note>
</relatedItem>

</relatedItem>
<relatedItem type="constituent">
<titleInfo>
<title>Don't Use the Tractors</title>
</titleInfo>
<name type="personal">
<namePart>Herman, Fred</namePart>
<role>
<roleTerm>lyricist</roleTerm>
</role>
</name>
<relatedItem type="preceding">
<titleInfo>
<title>Waltzing Matilda</title>
</titleInfo>
<note>Tune used or parodied</note>
</relatedItem>
</relatedItem>

<relatedItem type="constituent">
<titleInfo>
<title>Latest News Update</title>
</titleInfo>
<name type="personal">
<namePart>Feld, Harold</namePart>
<role>
<roleTerm>lyricist</roleTerm>
</role>
</name>
<relatedItem type="preceding">
<titleInfo>
<title>Last Night I Had the Strangest Dream</title>
</titleInfo>
<name type="personal">
<namePart>McCurdy, Ed</namePart>
<role>
<roleTerm>composer</roleTerm>
</role>
</name>
<note>Tune used or parodied</note>
</relatedItem>

</relatedItem>
<relatedItem type="constituent">
<titleInfo>
<title>The Fifty-Ninth Street Moggie Song</title>
</titleInfo>
<name type="personal">
<namePart>Eney, Richard</namePart>
<role>
<roleTerm>lyricist</roleTerm>
</role>
</name>
<relatedItem type="preceding">
<titleInfo>
<title>The Fifty-Ninth Street Bridge Song</title>
</titleInfo>
<name type="personal">
<namePart>Simon, Paul</namePart>
<role>
<roleTerm>composer</roleTerm>
</role>
</name>
<name type="personal">
<namePart>Garfunkel, Art</namePart>
<role>
<roleTerm>composer</roleTerm>
</role>
</name>
<note>Tune used or parodied</note>
</relatedItem>

</relatedItem>
<relatedItem type="constituent">
<titleInfo>
<title>We Are the Borg</title>
</titleInfo>
<name type="personal">
<namePart>Hykes, Muriel</namePart>
<role>
<roleTerm>lyricist</roleTerm>
</role>
</name>
<name type="personal">
<namePart>Shuch, H. Paul</namePart>
<role>
<roleTerm>lyricist</roleTerm>
</role>
</name>
<relatedItem type="preceding">
<titleInfo>
<title>I Am a Rock</title>
</titleInfo>
<name type="personal">
<namePart>Simon, Paul</namePart>
<role>
<roleTerm>composer</roleTerm>
</role>
</name>
<note>Tune used or parodied</note>
</relatedItem>

</relatedItem>
<relatedItem type="constituent">
<titleInfo>
<title>Bat Fax</title>
</titleInfo>
<name type="personal">
<namePart>Tucker, David</namePart>
<role>
<roleTerm>lyricist</roleTerm>
</role>
</name>
<relatedItem type="preceding">
<titleInfo>
<title>Sick Note</title>
</titleInfo>
<name type="personal">
<namePart>Cooksey, Pat</namePart>
<role>
<roleTerm>composer</roleTerm>
</role>
</name>
<note>Tune used or parodied</note>
</relatedItem>
</relatedItem>

<relatedItem type="constituent">
<titleInfo>
<title>Healthy Thinking</title>
</titleInfo>
<name type="personal">
<namePart>Ehrlich, Gary</namePart>
<role>
<roleTerm>lyricist</roleTerm>
</role>
</name>
<relatedItem type="preceding">
<titleInfo>
<title>Wishful Thinking</title>
</titleInfo>
<name type="personal">
<namePart>Thiesen, Alan</namePart>
<role>
<roleTerm>composer</roleTerm>
</role>
</name>
<note>Tune used or parodied</note>
</relatedItem>

</relatedItem>
<relatedItem type="constituent">
<titleInfo>
<title>Guardian of the Night</title>
</titleInfo>
<name type="personal">
<namePart>Kelson, Jan</namePart>
<role>
<roleTerm>lyricist</roleTerm>
</role>
</name>
<relatedItem type="preceding">
<titleInfo>
<title>Guardian of the Night</title>
</titleInfo>
<name type="personal">
<namePart>Davis, Meg</namePart>
<role>
<roleTerm>composer</roleTerm>
</role>
</name>
<note>Tune used or parodied</note>
</relatedItem>

</relatedItem>
<relatedItem type="constituent">
<titleInfo>
<title>The Bard and the Bees</title>
</titleInfo>
<name type="personal">
<namePart>MacRobb, Andrew</namePart>
<role>
<roleTerm>lyricist</roleTerm>
</role>
</name>
<relatedItem type="preceding">
<titleInfo>
<title>The Wild Rover</title>
</titleInfo>
<note>Tune used or parodied</note>
</relatedItem>

</relatedItem>
<relatedItem type="constituent">
<titleInfo>
<title>For Larry</title>
</titleInfo>
<name type="personal">
<namePart>Wessels, Mary Ellen</namePart>
<role>
<roleTerm>lyricist</roleTerm>
</role>
</name>
<name type="personal">
<namePart>Hayman, Judith</namePart>
<role>
<roleTerm>composer</roleTerm>
</role>
</name>
<typeOfResource>text</typeOfResource>
<typeOfResource>notated music</typeOfResource>
</relatedItem>

<relatedItem type="constituent">
<titleInfo>
<title>Shrink Wrap Blues</title>
</titleInfo>
<name type="personal">
<namePart>McGath, Gary</namePart>
<role>
<roleTerm>lyricist</roleTerm>
<roleTerm>composer</roleTerm>
</role>
</name>
<typeOfResource>text</typeOfResource>
<typeOfResource>notated music</typeOfResource>
</relatedItem>

<relatedItem type="constituent">
<titleInfo>
<title>The Fair Folk</title>
</titleInfo>
<name type="personal">
<namePart>Hayman, Judith</namePart>
<role>
<roleTerm>lyricist</roleTerm>
<roleTerm>composer</roleTerm>
</role>
</name>
<typeOfResource>text</typeOfResource>
<typeOfResource>notated music</typeOfResource>
</relatedItem>

<relatedItem type="constituent">
<titleInfo>
<title>Flying Stone</title>
</titleInfo>
<name type="personal">
<namePart>Cinii, I Abra</namePart>
<role>
<roleTerm>lyricist</roleTerm>
<roleTerm>composer</roleTerm>
</role>
</name>
<typeOfResource>text</typeOfResource>
<typeOfResource>notated music</typeOfResource>
</relatedItem>

<relatedItem type="constituent">
<titleInfo>
<title>Carcass</title>
</titleInfo>
<name type="personal">
<namePart>Mike Browne</namePart>
<role>
<roleTerm>lyricist</roleTerm>
</role>
</name>
<relatedItem type="preceding">
<titleInfo>
<title>Darkness</title>
</titleInfo>
<name type="personal">
<namePart>Kare, Jordin</namePart>
<role>
<roleTerm>composer</roleTerm>
</role>
</name>
<note>Tune used or parodied</note>
</relatedItem>
</relatedItem>

<relatedItem type="constituent">
<titleInfo>
<title>My Favorite Drug</title>
</titleInfo>
<name type="personal">
<namePart>Grumer, Avram</namePart>
<role>
<roleTerm>lyricist</roleTerm>
</role>
</name>
<relatedItem type="preceding">
<titleInfo>
<title>My Favorite Things</title>
</titleInfo>
<name type="personal">
<namePart>Rodgers, Richard</namePart>
<role>
<roleTerm>composer</roleTerm>
</role>
</name>
<note>Tune used or parodied</note>
</relatedItem>
</relatedItem>

<relatedItem type="constituent">
<titleInfo>
<title>Puppies Cooked in Brine</title>
</titleInfo>
<name type="personal">
<namePart>Ohi, Debbie Ridpath</namePart>
<role>
<roleTerm>lyricist</roleTerm>
<roleTerm>composer</roleTerm>
</role>
</name>
<typeOfResource>text</typeOfResource>
<typeOfResource>notated music</typeOfResource>
</relatedItem>

<relatedItem type="constituent">
<titleInfo>
<title>Joke Chrétien</title>
</titleInfo>
<relatedItem type="preceding">
<titleInfo>
<title>Jacques Chrétien</title>
</titleInfo>
<name type="personal">
<namePart>Dickson, Gordon</namePart>
<role>
<roleTerm>author</roleTerm>
</role>
</name>
<note>Tune used or parodied</note>
</relatedItem>
</relatedItem>

</mods>