<?xml version="1.0" encoding="UTF-8"?>
<?xml-stylesheet href="stylesheets/modshtml.xsl" type="text/xsl" ?>
<mods  version="3.1" xmlns="http://www.loc.gov/mods/v3" ID="filksongsthatgobump">
<recordInfo>
<recordCreationDate>2008-01-22</recordCreationDate>
<recordChangeDate>2009-09-24</recordChangeDate>
<!-- If you modify this file, please update the recordChangeDate element -->
</recordInfo>
<titleInfo>
<title>Filksongs That Go Bump in the Night</title>
</titleInfo>
<language>
<languageTerm type="code" authority="iso639-2b">eng</languageTerm>
</language>
<physicalDescription>
<form authority="marcform">print</form>
<extent>38 pages</extent>
<note>Loose pages, single sided, hand-punched</note>
</physicalDescription>
<originInfo>
<publisher>Old Collinwood Publishing House</publisher>
<dateIssued>1983</dateIssued>
</originInfo>
<name type="personal">
<namePart>Christy, JoAnn</namePart>
<role>
<roleTerm>editor</roleTerm>
</role>
<role>
<roleTerm>illustrator</roleTerm>
</role>
</name>
<name type="personal">
<namePart>Robin, Marcy</namePart>
<role>
<roleTerm>editor</roleTerm>
</role>
</name>
<name type="personal">
<namePart>Frankel, Alison Dayne</namePart>
<role>
<roleTerm>illustrator</roleTerm>
</role>
</name>

<relatedItem type="constituent">
  <titleInfo>
   <title>Dan Curtis' Dream</title>
  </titleInfo>
  <name type="personal">
      <namePart>Gerard, Aline</namePart>
     <role>
       <roleTerm>lyricist</roleTerm>
     </role>
  </name>
  <relatedItem type="preceding">
      <titleInfo>
       <title>The Camptown Races</title>
      </titleInfo>
      <name type="personal">
        <namePart>Foster, Stephen</namePart>
        <role>
          <roleTerm>composer</roleTerm>
        </role>
      </name>
      <note>Tune suggested or parodied</note>
  </relatedItem>
  <typeOfResource>text</typeOfResource>
</relatedItem>

<relatedItem type="constituent">
  <titleInfo>
   <title>The Twelve Days of DS</title>
  </titleInfo>
  <name type="personal">
      <namePart>Nelson, Kristi</namePart>
     <role>
       <roleTerm>lyricist</roleTerm>
     </role>
  </name>
  <relatedItem type="preceding">
      <titleInfo>
       <title>Twelve Days of Christmas</title>
      </titleInfo>
      <note>Tune suggested or parodied</note>
  </relatedItem>
  <typeOfResource>text</typeOfResource>
</relatedItem>

<relatedItem type="constituent">
  <titleInfo>
   <title>Oh Collinwood, Oh Collinwood!</title>
  </titleInfo>
  <name type="personal">
      <namePart>Franks, Bonnie</namePart>
     <role>
       <roleTerm>lyricist</roleTerm>
     </role>
  </name>
  <relatedItem type="preceding">
      <titleInfo>
       <title>O Tannenbaum</title>
      </titleInfo>
      <note>Tune suggested or parodied</note>
  </relatedItem>
  <typeOfResource>text</typeOfResource>
</relatedItem>

<relatedItem type="constituent">
  <titleInfo>
   <title>Enter at Your Own Risk</title>
  </titleInfo>
  <name type="personal">
      <namePart>Nelson, Kristi</namePart>
     <role>
       <roleTerm>lyricist</roleTerm>
     </role>
  </name>
  <relatedItem type="preceding">
      <titleInfo>
       <title>Camelot</title>
      </titleInfo>
      <name type="personal">
        <namePart>Loewe, Frederick</namePart>
        <role>
          <roleTerm>composer</roleTerm>
        </role>
      </name>
      <note>Tune suggested or parodied</note>
  </relatedItem>
  <typeOfResource>text</typeOfResource>
</relatedItem>

<relatedItem type="constituent">
  <titleInfo>
   <title>The Collins Clan</title>
  </titleInfo>
  <name type="personal">
      <namePart>Paige, Lori</namePart>
     <role>
       <roleTerm>lyricist</roleTerm>
     </role>
  </name>
  <relatedItem type="preceding">
      <titleInfo>
       <title>The Way We Were</title>
      </titleInfo>
      <note>Tune suggested or parodied</note>
  </relatedItem>
  <typeOfResource>text</typeOfResource>
</relatedItem>

<relatedItem type="constituent">
  <titleInfo>
   <title>You're Gonna Lose Your Head!</title>
  </titleInfo>
  <name type="personal">
      <namePart>Clark, Melody</namePart>
     <role>
       <roleTerm>lyricist</roleTerm>
     </role>
  </name>
  <name type="personal">
      <namePart>Robin, Marcy</namePart>
     <role>
       <roleTerm>lyricist</roleTerm>
     </role>
  </name>
  <relatedItem type="preceding">
      <titleInfo>
       <title>You're Gonna Lose That Girl</title>
      </titleInfo>
      <note>Tune suggested or parodied</note>
  </relatedItem>
  <typeOfResource>text</typeOfResource>
</relatedItem>

<relatedItem type="constituent">
  <titleInfo>
   <title>Barnabas</title>
  </titleInfo>
  <name type="personal">
      <namePart>Wylie, Susan</namePart>
     <role>
       <roleTerm>lyricist</roleTerm>
     </role>
  </name>
  <relatedItem type="preceding">
      <titleInfo>
       <title>Clementine</title>
      </titleInfo>
      <note>Tune suggested or parodied</note>
  </relatedItem>
  <typeOfResource>text</typeOfResource>
</relatedItem>

<relatedItem type="constituent">
  <titleInfo>
   <title>Willie's Lament</title>
  </titleInfo>
  <name type="personal">
      <namePart>Franks, Bonnie</namePart>
     <role>
       <roleTerm>lyricist</roleTerm>
     </role>
  </name>
  <relatedItem type="preceding">
      <titleInfo>
       <title>Clementine</title>
      </titleInfo>
      <note>Tune suggested or parodied</note>
  </relatedItem>
  <typeOfResource>text</typeOfResource>
</relatedItem>

<relatedItem type="constituent">
  <titleInfo>
   <title>Hello, Maggie!</title>
  </titleInfo>
  <name type="personal">
      <namePart>Myers, James E.</namePart>
     <role>
       <roleTerm>lyricist</roleTerm>
     </role>
  </name>
  <relatedItem type="preceding">
      <titleInfo>
       <title>Hello, Dolly!</title>
      </titleInfo>
      <name type="personal">
        <namePart>Herman, Jerry</namePart>
        <role>
          <roleTerm>composer</roleTerm>
        </role>
      </name>
      <note>Tune suggested or parodied</note>
  </relatedItem>
  <typeOfResource>text</typeOfResource>
</relatedItem>

<relatedItem type="constituent">
  <titleInfo>
   <title>Old MacCollins</title>
  </titleInfo>
  <name type="personal">
      <namePart>Beaston, James, Jr.</namePart>
     <role>
       <roleTerm>lyricist</roleTerm>
     </role>
  </name>
  <relatedItem type="preceding">
      <titleInfo>
       <title>Old MacDonald Had a Farm</title>
      </titleInfo>
      <note>Tune suggested or parodied</note>
  </relatedItem>
  <typeOfResource>text</typeOfResource>
</relatedItem>

<relatedItem type="constituent">
  <titleInfo>
   <title>I Saw Josette Kissing Barnabas</title>
  </titleInfo>
  <name type="personal">
      <namePart>Nelson, Kristi</namePart>
     <role>
       <roleTerm>lyricist</roleTerm>
     </role>
  </name>
  <relatedItem type="preceding">
      <titleInfo>
       <title>I Saw Mommy Kissing Santa Claus</title>
      </titleInfo>
      <note>Tune suggested or parodied</note>
  </relatedItem>
  <typeOfResource>text</typeOfResource>
</relatedItem>

<relatedItem type="constituent">
  <titleInfo>
   <title>Sarah Collins</title>
  </titleInfo>
  <name type="personal">
      <namePart>Myers, James E.</namePart>
     <role>
       <roleTerm>lyricist</roleTerm>
     </role>
  </name>
  <relatedItem type="preceding">
      <titleInfo>
       <title>London Bridges</title>
      </titleInfo>
      <note>Tune suggested or parodied</note>
  </relatedItem>
  <typeOfResource>text</typeOfResource>
</relatedItem>

<relatedItem type="constituent">
  <titleInfo>
   <title>Vampire's Hunt</title>
  </titleInfo>
  <name type="personal">
      <namePart>Stenstrom, Carol</namePart>
     <role>
       <roleTerm>lyricist</roleTerm>
     </role>
  </name>
  <relatedItem type="preceding">
      <titleInfo>
       <title>Teddy Bears' Picnic</title>
      </titleInfo>
      <note>Tune suggested or parodied</note>
  </relatedItem>
  <typeOfResource>text</typeOfResource>
</relatedItem>

<relatedItem type="constituent">
  <titleInfo>
   <title>Leviathan in Love</title>
  </titleInfo>
  <name type="personal">
      <namePart>Crocker, Debbie</namePart>
     <role>
       <roleTerm>lyricist</roleTerm>
     </role>
  </name>
  <relatedItem type="preceding">
      <titleInfo>
       <title>Teenager in Love</title>
      </titleInfo>
      <note>Tune suggested or parodied</note>
  </relatedItem>
  <typeOfResource>text</typeOfResource>
</relatedItem>

<relatedItem type="constituent">
  <titleInfo>
   <title>You're a Thirsty Bat</title>
  </titleInfo>
  <name type="personal">
      <namePart>Crocker, Debbie</namePart>
     <role>
       <roleTerm>lyricist</roleTerm>
     </role>
  </name>
  <relatedItem type="preceding">
      <titleInfo>
       <title>You're a Grand Old Flag</title>
      </titleInfo>
      <name type="personal">
        <namePart>Cohan, George M.</namePart>
        <role>
          <roleTerm>composer</roleTerm>
        </role>
      </name>
      <note>Tune suggested or parodied</note>
  </relatedItem>
  <typeOfResource>text</typeOfResource>
</relatedItem>

<relatedItem type="constituent">
  <titleInfo>
   <title>Bloodthirsty Bats</title>
  </titleInfo>
  <name type="personal">
      <namePart>Christy, Jo Ann</namePart>
     <role>
       <roleTerm>lyricist</roleTerm>
     </role>
  </name>
  <name type="personal">
      <namePart>Robin, Marcy</namePart>
     <role>
       <roleTerm>lyricist</roleTerm>
     </role>
  </name>
  <relatedItem type="preceding">
      <titleInfo>
       <title>Stars and Stripes Forever</title>
      </titleInfo>
      <name type="personal">
        <namePart>Sousa, John Philip</namePart>
        <role>
          <roleTerm>composer</roleTerm>
        </role>
      </name>
      <note>Tune suggested or parodied</note>
  </relatedItem>
  <typeOfResource>text</typeOfResource>
</relatedItem>

<relatedItem type="constituent">
  <titleInfo>
   <title>Bite Three Times</title>
  </titleInfo>
  <name type="personal">
      <namePart>Kreuter, Debbie</namePart>
     <role>
       <roleTerm>lyricist</roleTerm>
     </role>
  </name>
  <name type="personal">
      <namePart>Nelson, Kristi</namePart>
     <role>
       <roleTerm>lyricist</roleTerm>
     </role>
  </name>
  <relatedItem type="preceding">
      <titleInfo>
       <title>Knock Three Times</title>
      </titleInfo>
      <note>Tune suggested or parodied</note>
  </relatedItem>
  <typeOfResource>text</typeOfResource>
</relatedItem>

<relatedItem type="constituent">
  <titleInfo>
   <title>I'm Looking Over a Secret Panel</title>
  </titleInfo>
  <name type="personal">
      <namePart>Myers, James E.</namePart>
     <role>
       <roleTerm>lyricist</roleTerm>
     </role>
  </name>
  <relatedItem type="preceding">
      <titleInfo>
       <title>I'm Looking Over a Four-Leaf Clover</title>
      </titleInfo>
      <note>Tune suggested or parodied</note>
  </relatedItem>
  <typeOfResource>text</typeOfResource>
</relatedItem>

<relatedItem type="constituent">
  <titleInfo>
   <title>You'll Never Walk Alone</title>
  </titleInfo>
  <name type="personal">
      <namePart>Myers, James E.</namePart>
     <role>
       <roleTerm>lyricist</roleTerm>
     </role>
  </name>
  <relatedItem type="preceding">
      <titleInfo>
       <title>You'll Never Walk Alone</title>
      </titleInfo>
      <name type="personal">
        <namePart>Rodgers, Richard</namePart>
        <role>
          <roleTerm>composer</roleTerm>
        </role>
      </name>
      <note>Tune suggested or parodied</note>
  </relatedItem>
  <typeOfResource>text</typeOfResource>
</relatedItem>

<relatedItem type="constituent">
  <titleInfo>
   <title>The "Wurst" Song</title>
  </titleInfo>
  <name type="personal">
      <namePart>Crocker, Debbie</namePart>
     <role>
       <roleTerm>lyricist</roleTerm>
     </role>
  </name>
  <relatedItem type="preceding">
      <titleInfo>
       <title>Witch Doctor</title>
      </titleInfo>
      <note>Tune suggested or parodied</note>
  </relatedItem>
  <typeOfResource>text</typeOfResource>
</relatedItem>

<relatedItem type="constituent">
  <titleInfo>
   <title>Give Me Blood!</title>
  </titleInfo>
  <name type="personal">
      <namePart>Robin, Marcy</namePart>
     <role>
       <roleTerm>lyricist</roleTerm>
     </role>
  </name>
  <relatedItem type="preceding">
      <titleInfo>
       <title>Bye, Bye, Love</title>
      </titleInfo>
      <note>Tune suggested or parodied</note>
  </relatedItem>
  <typeOfResource>text</typeOfResource>
</relatedItem>

<relatedItem type="constituent">
  <titleInfo>
   <title>You Are My Bloodtype</title>
  </titleInfo>
  <name type="personal">
      <namePart>Myers, James E.</namePart>
     <role>
       <roleTerm>lyricist</roleTerm>
     </role>
  </name>
  <relatedItem type="preceding">
      <titleInfo>
       <title>You Are My Sunshine</title>
      </titleInfo>
      <note>Tune suggested or parodied</note>
  </relatedItem>
  <typeOfResource>text</typeOfResource>
</relatedItem>

<relatedItem type="constituent">
  <titleInfo>
   <title>I've Grown Accustomed to Her Bite</title>
  </titleInfo>
  <name type="personal">
      <namePart>Myers, James E.</namePart>
     <role>
       <roleTerm>lyricist</roleTerm>
     </role>
  </name>
  <relatedItem type="preceding">
      <titleInfo>
       <title>I've Grown Accustomed to Her Face</title>
      </titleInfo>
      <name type="personal">
        <namePart>Loewe, Frederick</namePart>
        <role>
          <roleTerm>composer</roleTerm>
        </role>
      </name>
      <note>Tune suggested or parodied</note>
  </relatedItem>
  <typeOfResource>text</typeOfResource>
</relatedItem>

<relatedItem type="constituent">
  <titleInfo>
   <title>Nosferatu</title>
  </titleInfo>
  <name type="personal">
      <namePart>Frankel, Alison Dayne</namePart>
     <role>
       <roleTerm>lyricist</roleTerm>
     </role>
  </name>
  <relatedItem type="preceding">
      <titleInfo>
       <title>Oklahoma</title>
      </titleInfo>
      <name type="personal">
        <namePart>Rodgers, Richard</namePart>
        <role>
          <roleTerm>composer</roleTerm>
        </role>
      </name>
      <note>Tune suggested or parodied</note>
  </relatedItem>
  <typeOfResource>text</typeOfResource>
</relatedItem>

<relatedItem type="constituent">
  <titleInfo>
   <title>Dr. Frankenstein</title>
  </titleInfo>
  <name type="personal">
      <namePart>Myers, James E.</namePart>
     <role>
       <roleTerm>lyricist</roleTerm>
     </role>
  </name>
  <relatedItem type="preceding">
      <titleInfo>
       <title>The Candy Man</title>
      </titleInfo>
      <note>Tune suggested or parodied</note>
  </relatedItem>
  <typeOfResource>text</typeOfResource>
</relatedItem>

<relatedItem type="constituent">
  <titleInfo>
   <title>Oh, My Darling Frankenstein</title>
  </titleInfo>
  <name type="personal">
      <namePart>Kendall, Deanne</namePart>
     <role>
       <roleTerm>lyricist</roleTerm>
     </role>
  </name>
  <relatedItem type="preceding">
      <titleInfo>
       <title>Clementine</title>
      </titleInfo>
      <note>Tune suggested or parodied</note>
  </relatedItem>
  <typeOfResource>text</typeOfResource>
</relatedItem>

<relatedItem type="constituent">
  <titleInfo>
   <title>Call Me Lycanthropic</title>
  </titleInfo>
  <name type="personal">
      <namePart>Myers, James E.</namePart>
     <role>
       <roleTerm>lyricist</roleTerm>
     </role>
  </name>
  <relatedItem type="preceding">
      <titleInfo>
       <title>Call Me Irresponsible</title>
      </titleInfo>
      <note>Tune suggested or parodied</note>
  </relatedItem>
  <typeOfResource>text</typeOfResource>
</relatedItem>

<relatedItem type="constituent">
  <titleInfo>
   <title>Hush, Little Baby</title>
  </titleInfo>
  <name type="personal">
      <namePart>Myers, James E.</namePart>
     <role>
       <roleTerm>lyricist</roleTerm>
     </role>
  </name>
  <relatedItem type="preceding">
      <titleInfo>
       <title>Hush, Little Baby</title>
      </titleInfo>
      <note>Tune suggested or parodied</note>
  </relatedItem>
  <typeOfResource>text</typeOfResource>
</relatedItem>

<relatedItem type="constituent">
  <titleInfo>
   <title>Bitten Again</title>
  </titleInfo>
  <name type="personal">
      <namePart>Kreuter, Debbie</namePart>
     <role>
       <roleTerm>lyricist</roleTerm>
     </role>
  </name>
  <name type="personal">
      <namePart>Nelson, Kristi</namePart>
     <role>
       <roleTerm>lyricist</roleTerm>
     </role>
  </name>
  <relatedItem type="preceding">
      <titleInfo>
       <title>Hello Again</title>
      </titleInfo>
      <name type="personal">
        <namePart>Diamond, Neil</namePart>
        <role>
          <roleTerm>composer</roleTerm>
        </role>
      </name>
      <note>Tune suggested or parodied</note>
  </relatedItem>
  <typeOfResource>text</typeOfResource>
</relatedItem>

<relatedItem type="constituent">
  <titleInfo>
   <title>Save Me</title>
  </titleInfo>
  <name type="personal">
      <namePart>Myers, James E.</namePart>
     <role>
       <roleTerm>lyricist</roleTerm>
     </role>
  </name>
  <relatedItem type="preceding">
      <titleInfo>
       <title>Play Me</title>
      </titleInfo>
      <name type="personal">
        <namePart>Diamond, Neil</namePart>
        <role>
          <roleTerm>composer</roleTerm>
        </role>
      </name>
      <note>Tune suggested or parodied</note>
  </relatedItem>
  <typeOfResource>text</typeOfResource>
</relatedItem>

<relatedItem type="constituent">
  <titleInfo>
   <title>Vampire's Call</title>
  </titleInfo>
  <name type="personal">
      <namePart>Nash, Esther</namePart>
     <role>
       <roleTerm>lyricist</roleTerm>
     </role>
  </name>
  <relatedItem type="preceding">
      <titleInfo>
       <title>Autumn Leaves</title>
      </titleInfo>
      <note>Tune suggested or parodied</note>
  </relatedItem>
  <typeOfResource>text</typeOfResource>
</relatedItem>

<relatedItem type="constituent">
  <titleInfo>
   <title>Be Patient Just a Little More</title>
  </titleInfo>
  <name type="personal">
      <namePart>Myers, James E.</namePart>
     <role>
       <roleTerm>lyricist</roleTerm>
     </role>
  </name>
  <relatedItem type="preceding">
      <titleInfo>
       <title>I'll Have to Say "I Love You" in a Song</title>
      </titleInfo>
      <note>Tune suggested or parodied</note>
  </relatedItem>
  <typeOfResource>text</typeOfResource>
</relatedItem>

<relatedItem type="constituent">
  <titleInfo>
   <title>Coffins in the Ground</title>
  </titleInfo>
  <name type="personal">
      <namePart>Myers, James E.</namePart>
     <role>
       <roleTerm>lyricist</roleTerm>
     </role>
  </name>
  <relatedItem type="preceding">
      <titleInfo>
       <title>Castles in the Air</title>
      </titleInfo>
      <note>Tune suggested or parodied</note>
  </relatedItem>
  <typeOfResource>text</typeOfResource>
</relatedItem>

<relatedItem type="constituent">
  <titleInfo>
   <title>At Collinwood</title>
  </titleInfo>
  <name type="personal">
      <namePart>Myers, James E.</namePart>
     <role>
       <roleTerm>lyricist</roleTerm>
     </role>
  </name>
  <relatedItem type="preceding">
      <titleInfo>
       <title>At Seventeen</title>
      </titleInfo>
      <note>Tune suggested or parodied</note>
  </relatedItem>
  <typeOfResource>text</typeOfResource>
</relatedItem>

<relatedItem type="constituent">
  <titleInfo>
   <title>The Dark and Gloomy House</title>
  </titleInfo>
  <name type="personal">
      <namePart>Hann, Tari</namePart>
     <role>
       <roleTerm>lyricist</roleTerm>
     </role>
  </name>
  <relatedItem type="preceding">
      <titleInfo>
       <title>The Long and Winding Road</title>
      </titleInfo>
      <note>Tune suggested or parodied</note>
  </relatedItem>
  <typeOfResource>text</typeOfResource>
</relatedItem>

<relatedItem type="constituent">
  <titleInfo>
   <title>The Big House on the Cliff</title>
  </titleInfo>
  <name type="personal">
      <namePart>Klapper, Beth</namePart>
     <role>
       <roleTerm>lyricist</roleTerm>
     </role>
  </name>
  <name type="personal">
      <namePart>Clark, Melody</namePart>
     <role>
       <roleTerm>lyricist</roleTerm>
     </role>
  </name>
  <relatedItem type="preceding">
      <titleInfo>
       <title>O Tannenbaum</title>
      </titleInfo>
      <note>Tune suggested or parodied</note>
  </relatedItem>
  <typeOfResource>text</typeOfResource>
</relatedItem>

<relatedItem type="constituent">
  <titleInfo>
   <title>O'er in the Old House</title>
  </titleInfo>
  <name type="personal">
      <namePart>Myers, James E.</namePart>
     <role>
       <roleTerm>lyricist</roleTerm>
     </role>
  </name>
  <relatedItem type="preceding">
      <titleInfo>
       <title>Down in the Valley</title>
      </titleInfo>
      <note>Tune suggested or parodied</note>
  </relatedItem>
  <typeOfResource>text</typeOfResource>
</relatedItem>

<relatedItem type="constituent">
  <titleInfo>
   <title>A Love Undying</title>
  </titleInfo>
  <name type="personal">
      <namePart>Myers, James E.</namePart>
     <role>
       <roleTerm>lyricist</roleTerm>
     </role>
  </name>
  <relatedItem type="preceding">
      <titleInfo>
       <title>Greensleeves</title>
      </titleInfo>
      <note>Tune suggested or parodied</note>
  </relatedItem>
  <typeOfResource>text</typeOfResource>
</relatedItem>

<relatedItem type="constituent">
  <titleInfo>
   <title>You Are My Special Victim</title>
  </titleInfo>
  <name type="personal">
      <namePart>Crocker, Debbie</namePart>
     <role>
       <roleTerm>lyricist</roleTerm>
     </role>
  </name>
  <relatedItem type="preceding">
      <titleInfo>
       <title>You Are My Special Angel</title>
      </titleInfo>
      <note>Tune suggested or parodied</note>
  </relatedItem>
  <typeOfResource>text</typeOfResource>
</relatedItem>

<relatedItem type="constituent">
  <titleInfo>
   <title>Scarlet Kisses</title>
   <subTitle>(For Her Neck)</subTitle>
  </titleInfo>
  <name type="personal">
      <namePart>Crocker, Debbie</namePart>
     <role>
       <roleTerm>lyricist</roleTerm>
     </role>
  </name>
  <relatedItem type="preceding">
      <titleInfo>
       <title>Scarlet Ribbons</title>
      </titleInfo>
      <note>Tune suggested or parodied</note>
  </relatedItem>
  <typeOfResource>text</typeOfResource>
</relatedItem>

<relatedItem type="constituent">
  <titleInfo>
   <title>Willie's Song</title>
  </titleInfo>
  <name type="personal">
      <namePart>Hann, Tari</namePart>
     <role>
       <roleTerm>lyricist</roleTerm>
     </role>
  </name>
  <relatedItem type="preceding">
      <titleInfo>
       <title>Black Water</title>
      </titleInfo>
      <note>Tune suggested or parodied</note>
  </relatedItem>
  <typeOfResource>text</typeOfResource>
</relatedItem>

<relatedItem type="constituent">
  <titleInfo>
   <title>Wait 'til the Sun Shines, Maggie</title>
  </titleInfo>
  <name type="personal">
      <namePart>Hann, Tari</namePart>
     <role>
       <roleTerm>lyricist</roleTerm>
     </role>
  </name>
  <relatedItem type="preceding">
      <titleInfo>
       <title>Wait 'til the Sun Shines, Nelly</title>
      </titleInfo>
      <note>Tune suggested or parodied</note>
  </relatedItem>
  <typeOfResource>text</typeOfResource>
</relatedItem>

<relatedItem type="constituent">
  <titleInfo>
   <title>Reflections</title>
  </titleInfo>
  <name type="personal">
      <namePart>Stenstrom, Carol</namePart>
     <role>
       <roleTerm>lyricist</roleTerm>
     </role>
     <role>
       <roleTerm>composer</roleTerm>
     </role>
  </name>
  <typeOfResource>text</typeOfResource>
  <typeOfResource>notated music</typeOfResource>
</relatedItem>

<relatedItem type="constituent">
  <titleInfo>
   <title>Both Sides Now</title>
  </titleInfo>
  <name type="personal">
      <namePart>Myers, James E.</namePart>
     <role>
       <roleTerm>lyricist</roleTerm>
     </role>
  </name>
  <relatedItem type="preceding">
      <titleInfo>
       <title>Both Sides Now</title>
      </titleInfo>
      <note>Tune suggested or parodied</note>
  </relatedItem>
  <typeOfResource>text</typeOfResource>
</relatedItem>

<relatedItem type="constituent">
  <titleInfo>
   <title>Salute to Shadowcon</title>
  </titleInfo>
  <relatedItem type="preceding">
      <titleInfo>
       <title>Battle Hymn of the Republic</title>
      </titleInfo>
      <note>Tune suggested or parodied</note>
  </relatedItem>
  <typeOfResource>text</typeOfResource>
</relatedItem>




</mods>
