<?xml version="1.0" encoding="UTF-8"?>
<?xml-stylesheet href="stylesheets/modshtml.xsl" type="text/xsl" ?>
<mods  version="3.1" xmlns="http://www.loc.gov/mods/v3" ID="onthefilkroad">
<recordInfo>
<recordCreationDate>2009-01-25</recordCreationDate>
<recordChangeDate>2009-01-25</recordChangeDate>
<!-- If you modify this file, please update the recordChangeDate element -->
</recordInfo>
<titleInfo>
<title>On the Filk Road</title>
</titleInfo>
<identifier type="isbn">9781-870824-55-2</identifier>
<language>
<languageTerm type="code" authority="iso639-2b">eng</languageTerm>
</language>
<physicalDescription>
<form authority="marcform">print</form>
<note>Paperback, 156 pages. A4 wiro-bound.</note>
</physicalDescription>
<abstract>Songbook for aXXidental, the 2009 British filk convention</abstract>
<originInfo>
<place>
  <placeTerm type="text">England</placeTerm>
</place>
<publisher>Beccon Publications</publisher>
<dateIssued>2009-02-06</dateIssued>
</originInfo>
<name type="personal">
<namePart>Richards, Alison</namePart>
<role>
<roleTerm>editor</roleTerm>
</role>
</name>

<relatedItem type="constituent">
  <titleInfo>
   <title>Festival of Song</title>
   <subTitle>A Grace Before Filk</subTitle>
  </titleInfo>
  <name type="personal">
      <namePart>Housden, Valerie</namePart>
     <role>
       <roleTerm>lyricist</roleTerm>
     </role>
  </name>
  <typeOfResource>text</typeOfResource>
</relatedItem>

<relatedItem type="constituent">
  <titleInfo>
   <title>Introduction</title>
  </titleInfo>
  <name type="personal">
      <namePart>Housden, Valerie</namePart>
     <role>
       <roleTerm>lyricist</roleTerm>
     </role>
  </name>
  <typeOfResource>text</typeOfResource>
</relatedItem>

<relatedItem type="constituent">
  <titleInfo>
   <title>Dragon Connection</title>
  </titleInfo>
  <name type="personal">
      <namePart>Titman, Nat</namePart>
     <role>
       <roleTerm>lyricist</roleTerm>
     </role>
  </name>
  <typeOfResource>text</typeOfResource>
</relatedItem>

<relatedItem type="constituent">
  <titleInfo>
   <title>Where Pigs Have Wings</title>
  </titleInfo>
  <name type="personal">
      <namePart>James, Rhodri</namePart>
     <role>
       <roleTerm>lyricist</roleTerm>
     </role>
  </name>
  <typeOfResource>text</typeOfResource>
</relatedItem>

<relatedItem type="constituent">
  <titleInfo>
   <title>Sang It Live</title>
  </titleInfo>
  <name type="personal">
      <namePart>Titman, Nat</namePart>
     <role>
       <roleTerm>lyricist</roleTerm>
     </role>
  </name>
  <typeOfResource>text</typeOfResource>
</relatedItem>

<relatedItem type="constituent">
  <titleInfo>
   <title>A Scottish Introduction</title>
  </titleInfo>
  <name type="personal">
      <namePart>Housden, Valerie</namePart>
     <role>
       <roleTerm>lyricist</roleTerm>
     </role>
  </name>
  <typeOfResource>text</typeOfResource>
</relatedItem>

<relatedItem type="constituent">
  <titleInfo>
   <title>When I Ran My First Con</title>
  </titleInfo>
  <name type="personal">
      <namePart>Barton, Andrew</namePart>
     <role>
       <roleTerm>lyricist</roleTerm>
     </role>
  </name>
  <typeOfResource>text</typeOfResource>
</relatedItem>

<relatedItem type="constituent">
  <titleInfo>
   <title>The Con Table</title>
  </titleInfo>
  <name type="personal">
      <namePart>Mandel, Mark A.</namePart>
     <role>
       <roleTerm>lyricist</roleTerm>
     </role>
  </name>
  <typeOfResource>text</typeOfResource>
</relatedItem>

<relatedItem type="constituent">
  <titleInfo>
   <title>I Can't Believe Phil Hasn't Done This One</title>
  </titleInfo>
  <name type="personal">
      <namePart>Nyrond, Zander</namePart>
     <role>
       <roleTerm>lyricist</roleTerm>
     </role>
  </name>
  <typeOfResource>text</typeOfResource>
</relatedItem>

<relatedItem type="constituent">
  <titleInfo>
   <title>Someone Else's Tune</title>
  </titleInfo>
  <name type="personal">
      <namePart>Soley, Kate</namePart>
     <role>
       <roleTerm>lyricist</roleTerm>
     </role>
  </name>
  <typeOfResource>text</typeOfResource>
</relatedItem>

<relatedItem type="constituent">
  <titleInfo>
   <title>Tru Story</title>
  </titleInfo>
  <name type="personal">
      <namePart>Mandel, Mark A.</namePart>
     <role>
       <roleTerm>lyricist</roleTerm>
     </role>
  </name>
  <typeOfResource>text</typeOfResource>
</relatedItem>


<relatedItem type="constituent">
  <titleInfo>
   <title>Keep It Unreal</title>
  </titleInfo>
  <name type="personal">
      <namePart>Nyrond, Zander</namePart>
     <role>
       <roleTerm>lyricist</roleTerm>
     </role>
  </name>
  <typeOfResource>text</typeOfResource>
</relatedItem>

<relatedItem type="constituent">
  <titleInfo>
   <title>Paper Worlds</title>
  </titleInfo>
  <name type="personal">
      <namePart>Kimberley, Talis</namePart>
     <role>
       <roleTerm>lyricist</roleTerm>
     </role>
  </name>
  <typeOfResource>text</typeOfResource>
</relatedItem>

<relatedItem type="constituent">
  <titleInfo>
   <title>Pictures in the Air</title>
  </titleInfo>
  <name type="personal">
      <namePart>Sampson, Mich</namePart>
     <role>
       <roleTerm>lyricist</roleTerm>
     </role>
  </name>
  <typeOfResource>text</typeOfResource>
</relatedItem>

<relatedItem type="constituent">
  <titleInfo>
   <title>Where Dragons Fly</title>
  </titleInfo>
  <name type="personal">
      <namePart>Richards, Mike</namePart>
     <role>
       <roleTerm>lyricist</roleTerm>
     </role>
  </name>
  <typeOfResource>text</typeOfResource>
</relatedItem>

<relatedItem type="constituent">
  <titleInfo>
   <title>Pilgrims and Travellers</title>
  </titleInfo>
  <name type="personal">
      <namePart>Dean, Lawrence</namePart>
     <role>
       <roleTerm>lyricist</roleTerm>
     </role>
  </name>
  <typeOfResource>text</typeOfResource>
</relatedItem>

<relatedItem type="constituent">
  <titleInfo>
   <title>Some Kind of Hero</title>
  </titleInfo>
  <name type="personal">
      <namePart>Richards, Mike</namePart>
     <role>
       <roleTerm>lyricist</roleTerm>
     </role>
  </name>
  <name type="personal">
      <namePart>Richards, Alison</namePart>
     <role>
       <roleTerm>lyricist</roleTerm>
     </role>
  </name>
  <typeOfResource>text</typeOfResource>
</relatedItem>

<relatedItem type="constituent">
  <titleInfo>
   <title>Autumn Sunset</title>
  </titleInfo>
  <name type="personal">
      <namePart>Prett, Alasdair</namePart>
     <role>
       <roleTerm>lyricist</roleTerm>
     </role>
  </name>
  <typeOfResource>text</typeOfResource>
</relatedItem>


<relatedItem type="constituent">
  <titleInfo>
   <title>Celtic Country</title>
  </titleInfo>
  <name type="personal">
      <namePart>Goss, Adam R.</namePart>
     <role>
       <roleTerm>lyricist</roleTerm>
     </role>
  </name>
  <typeOfResource>text</typeOfResource>
</relatedItem>

<relatedItem type="constituent">
  <titleInfo>
   <title>Another Woad Warrior Song</title>
  </titleInfo>
  <name type="personal">
      <namePart>Housden, Valerie</namePart>
     <role>
       <roleTerm>lyricist</roleTerm>
     </role>
  </name>
  <name type="personal">
      <namePart>Nyrond, Zander</namePart>
     <role>
       <roleTerm>lyricist</roleTerm>
     </role>
  </name>
  <typeOfResource>text</typeOfResource>
</relatedItem>

<relatedItem type="constituent">
  <titleInfo>
   <title>T. Rex-eteen</title>
  </titleInfo>
  <name type="personal">
      <namePart>Rosenfeld, Robert</namePart>
     <role>
       <roleTerm>lyricist</roleTerm>
     </role>
  </name>
  <typeOfResource>text</typeOfResource>
  <relatedItem type="preceding">
      <titleInfo>
       <title>Velveteen</title>
      </titleInfo>
      <name type="personal">
        <namePart>Mar, Kathy</namePart>
        <role>
          <roleTerm>composer</roleTerm>
        </role>
      </name>
      <note>Tune suggested or parodied</note>
  </relatedItem>
</relatedItem>

<relatedItem type="constituent">
  <titleInfo>
   <title>Pousse-Café</title>
  </titleInfo>
  <name type="personal">
      <namePart>Mandel, Mark A.</namePart>
     <role>
       <roleTerm>lyricist</roleTerm>
     </role>
  </name>
  <typeOfResource>text</typeOfResource>
</relatedItem>

<relatedItem type="constituent">
  <titleInfo>
   <title>The Unicorn's Lament</title>
  </titleInfo>
  <name type="personal">
      <namePart>Nanson, Tom</namePart>
     <role>
       <roleTerm>lyricist</roleTerm>
     </role>
  </name>
  <typeOfResource>text</typeOfResource>
</relatedItem>

<relatedItem type="constituent">
  <titleInfo>
   <title>Yesterday</title>
  </titleInfo>
  <name type="personal">
      <namePart>Thiesen, Alan</namePart>
     <role>
       <roleTerm>lyricist</roleTerm>
     </role>
  </name>
  <typeOfResource>text</typeOfResource>
</relatedItem>

<relatedItem type="constituent">
  <titleInfo>
   <title>Blue Cutie</title>
  </titleInfo>
  <name type="personal">
      <namePart>Soley, Kate</namePart>
     <role>
       <roleTerm>lyricist</roleTerm>
     </role>
  </name>
  <typeOfResource>text</typeOfResource>
</relatedItem>

<relatedItem type="constituent">
  <titleInfo>
   <title>Merry Solstice, Rhiannon Evenstar</title>
  </titleInfo>
  <name type="personal">
      <namePart>Freeman, Nancy Louise</namePart>
     <role>
       <roleTerm>lyricist</roleTerm>
     </role>
  </name>
  <typeOfResource>text</typeOfResource>
</relatedItem>

<relatedItem type="constituent">
  <titleInfo>
   <title>Triptych</title>
  </titleInfo>
  <name type="personal">
      <namePart>Kimberley, Talis</namePart>
     <role>
       <roleTerm>lyricist</roleTerm>
     </role>
  </name>
  <typeOfResource>text</typeOfResource>
</relatedItem>

<relatedItem type="constituent">
  <titleInfo>
   <title>Raven Waltz</title>
  </titleInfo>
  <name type="personal">
      <namePart>Honisch, Juliane</namePart>
     <role>
       <roleTerm>lyricist</roleTerm>
     </role>
  </name>
  <typeOfResource>text</typeOfResource>
</relatedItem>

<relatedItem type="constituent">
  <titleInfo>
   <title>One Small Boat</title>
  </titleInfo>
  <name type="personal">
      <namePart>Valtazanou, Marilisa</namePart>
     <role>
       <roleTerm>lyricist</roleTerm>
     </role>
  </name>
  <typeOfResource>text</typeOfResource>
</relatedItem>

<relatedItem type="constituent">
  <titleInfo>
   <title>The Beat of Drums</title>
  </titleInfo>
  <name type="personal">
      <namePart>Westhead, Peter</namePart>
     <role>
       <roleTerm>lyricist</roleTerm>
     </role>
  </name>
  <typeOfResource>text</typeOfResource>
</relatedItem>

<relatedItem type="constituent">
  <titleInfo>
   <title>Girls' Night Out</title>
  </titleInfo>
  <name type="personal">
      <namePart>Miki Dennis</namePart>
     <role>
       <roleTerm>lyricist</roleTerm>
     </role>
  </name>
  <typeOfResource>text</typeOfResource>
</relatedItem>

<relatedItem type="constituent">
  <titleInfo>
   <title>Bag Ladies</title>
  </titleInfo>
  <name type="personal">
      <namePart>Kimberley, Talis</namePart>
     <role>
       <roleTerm>lyricist</roleTerm>
     </role>
  </name>
  <typeOfResource>text</typeOfResource>
</relatedItem>

<relatedItem type="constituent">
  <titleInfo>
   <title>Captain Bugger All</title>
  </titleInfo>
  <name type="personal">
      <namePart>Dragster</namePart>
     <role>
       <roleTerm>lyricist</roleTerm>
     </role>
  </name>
  <typeOfResource>text</typeOfResource>
</relatedItem>

<relatedItem type="constituent">
  <titleInfo>
   <title>Weapons of Math Instruction</title>
  </titleInfo>
  <name type="personal">
      <namePart>Gladstone, Kate</namePart>
     <role>
       <roleTerm>lyricist</roleTerm>
     </role>
  </name>
  <relatedItem type="preceding">
      <titleInfo>
       <title>The Alternate World Temperance Union</title>
      </titleInfo>
      <name type="personal">
        <namePart>McGath, Gary</namePart>
        <role>
          <roleTerm>composer</roleTerm>
        </role>
      </name>
      <note>Tune suggested or parodied</note>
  </relatedItem>
  <typeOfResource>text</typeOfResource>
</relatedItem>

<relatedItem type="constituent">
  <titleInfo>
   <title>The Gasman Cometh Not</title>
  </titleInfo>
  <name type="personal">
      <namePart>Nyrond, Zander</namePart>
     <role>
       <roleTerm>lyricist</roleTerm>
     </role>
  </name>
  <typeOfResource>text</typeOfResource>
</relatedItem>

<relatedItem type="constituent">
  <titleInfo>
   <title>The Four Horsemen of the Apocrypha</title>
  </titleInfo>
  <name type="personal">
      <namePart>Dennis, Miki</namePart>
     <role>
       <roleTerm>lyricist</roleTerm>
     </role>
  </name>
  <typeOfResource>text</typeOfResource>
</relatedItem>

<relatedItem type="constituent">
  <titleInfo>
   <title>The Sheriff's Cunning Plan</title>
  </titleInfo>
  <name type="personal">
      <namePart>Soley, Kate</namePart>
     <role>
       <roleTerm>lyricist</roleTerm>
     </role>
  </name>
  <typeOfResource>text</typeOfResource>
</relatedItem>

<relatedItem type="constituent">
  <titleInfo>
   <title>The Twelve Days of Testing</title>
  </titleInfo>
  <name type="personal">
      <namePart>Bristow, Paul</namePart>
     <role>
       <roleTerm>lyricist</roleTerm>
     </role>
  </name>
  <typeOfResource>text</typeOfResource>
</relatedItem>

<relatedItem type="constituent">
  <titleInfo>
   <title>Metric Rules</title>
  </titleInfo>
  <name type="personal">
      <namePart>Gladstone, Kate</namePart>
     <role>
       <roleTerm>lyricist</roleTerm>
     </role>
  </name>
  <typeOfResource>text</typeOfResource>
</relatedItem>

<relatedItem type="constituent">
  <titleInfo>
   <title>Don't Wear the Beeper</title>
  </titleInfo>
  <name type="personal">
      <namePart>Freeman, Nancy Louise</namePart>
     <role>
       <roleTerm>lyricist</roleTerm>
     </role>
  </name>
  <typeOfResource>text</typeOfResource>
</relatedItem>

<relatedItem type="constituent">
  <titleInfo>
   <title>Baby with a Snooze Button</title>
  </titleInfo>
  <name type="personal">
      <namePart>Gordon-Kerr, Andy</namePart>
     <role>
       <roleTerm>lyricist</roleTerm>
     </role>
  </name>
  <name type="personal">
      <namePart>Gordon-Kerr, Martin</namePart>
     <role>
       <roleTerm>lyricist</roleTerm>
     </role>
  </name>
  <typeOfResource>text</typeOfResource>
</relatedItem>

<relatedItem type="constituent">
  <titleInfo>
   <title>American Play</title>
  </titleInfo>
  <name type="personal">
      <namePart>Dragster</namePart>
     <role>
       <roleTerm>lyricist</roleTerm>
     </role>
  </name>
  <typeOfResource>text</typeOfResource>
</relatedItem>

<relatedItem type="constituent">
  <titleInfo>
   <title>The Missing Blogger</title>
  </titleInfo>
  <name type="personal">
      <namePart>McGath, Gary</namePart>
     <role>
       <roleTerm>lyricist</roleTerm>
     </role>
  </name>
  <relatedItem type="preceding">
      <titleInfo>
       <title>The Frozen Logger</title>
      </titleInfo>
      <note>Tune suggested or parodied</note>
  </relatedItem>
  <typeOfResource>text</typeOfResource>
</relatedItem>

<relatedItem type="constituent">
  <titleInfo>
   <title>Accept No Substitutes</title>
  </titleInfo>
  <name type="personal">
      <namePart>Wynne, Rob</namePart>
     <role>
       <roleTerm>lyricist</roleTerm>
     </role>
  </name>
  <typeOfResource>text</typeOfResource>
</relatedItem>

<relatedItem type="constituent">
  <titleInfo>
   <title>Radioactive Tumbleweeds</title>
  </titleInfo>
  <name type="personal">
      <namePart>West, Julia</namePart>
     <role>
       <roleTerm>lyricist</roleTerm>
     </role>
  </name>
  <typeOfResource>text</typeOfResource>
</relatedItem>

<relatedItem type="constituent">
  <titleInfo>
   <title>A Spock with No Brain</title>
  </titleInfo>
  <name type="personal">
      <namePart>Goss, Adam</namePart>
     <role>
       <roleTerm>lyricist</roleTerm>
     </role>
  </name>
  <typeOfResource>text</typeOfResource>
</relatedItem>

<relatedItem type="constituent">
  <titleInfo>
   <title>The Tribble Song</title>
  </titleInfo>
  <name type="personal">
      <namePart>Titman, Nat</namePart>
     <role>
       <roleTerm>lyricist</roleTerm>
     </role>
  </name>
  <typeOfResource>text</typeOfResource>
</relatedItem>

<relatedItem type="constituent">
  <titleInfo>
   <title>Old Jim Kirk</title>
  </titleInfo>
  <name type="personal">
      <namePart>Biddle, Brian</namePart>
     <role>
       <roleTerm>lyricist</roleTerm>
     </role>
  </name>
  <typeOfResource>text</typeOfResource>
</relatedItem>

<relatedItem type="constituent">
  <titleInfo>
   <title>The Hunt</title>
  </titleInfo>
  <name type="personal">
      <namePart>Richards, Mike</namePart>
     <role>
       <roleTerm>lyricist</roleTerm>
     </role>
  </name>
  <name type="personal">
      <namePart>Richards, Alison</namePart>
     <role>
       <roleTerm>lyricist</roleTerm>
     </role>
  </name>
  <typeOfResource>text</typeOfResource>
</relatedItem>

<relatedItem type="constituent">
  <titleInfo>
   <title>This Lady Isn't Leaving</title>
  </titleInfo>
  <name type="personal">
      <namePart>Housden, Valerie</namePart>
     <role>
       <roleTerm>lyricist</roleTerm>
     </role>
  </name>
  <typeOfResource>text</typeOfResource>
</relatedItem>

<relatedItem type="constituent">
  <titleInfo>
   <title>Lady in Veils</title>
  </titleInfo>
  <name type="personal">
      <namePart>Housden, Valerie</namePart>
     <role>
       <roleTerm>lyricist</roleTerm>
     </role>
  </name>
  <typeOfResource>text</typeOfResource>
</relatedItem>

<relatedItem type="constituent">
  <titleInfo>
   <title>Mister Sandworm</title>
  </titleInfo>
  <name type="personal">
      <namePart>Biddle, Brian</namePart>
     <role>
       <roleTerm>lyricist</roleTerm>
     </role>
  </name>
  <typeOfResource>text</typeOfResource>
</relatedItem>

<relatedItem type="constituent">
  <titleInfo>
   <title>Starving</title>
  </titleInfo>
  <name type="personal">
      <namePart>Nanson, Tom</namePart>
     <role>
       <roleTerm>lyricist</roleTerm>
     </role>
  </name>
  <typeOfResource>text</typeOfResource>
</relatedItem>

<relatedItem type="constituent">
  <titleInfo>
   <title>Snowwatch</title>
  </titleInfo>
  <name type="personal">
      <namePart>Housden, Valerie</namePart>
     <role>
       <roleTerm>lyricist</roleTerm>
     </role>
  </name>
  <typeOfResource>text</typeOfResource>
</relatedItem>

<relatedItem type="constituent">
  <titleInfo>
   <title>Foundation's End</title>
  </titleInfo>
  <name type="personal">
      <namePart>Prett, Alasdair</namePart>
     <role>
       <roleTerm>lyricist</roleTerm>
     </role>
  </name>
  <typeOfResource>text</typeOfResource>
</relatedItem>

<relatedItem type="constituent">
  <titleInfo>
   <title>Empty Eyrie</title>
  </titleInfo>
  <name type="personal">
      <namePart>1/2mega</namePart>
     <role>
       <roleTerm>lyricist</roleTerm>
     </role>
  </name>
  <typeOfResource>text</typeOfResource>
</relatedItem>

<relatedItem type="constituent">
  <titleInfo>
   <title>Crisis on Ptarmigan</title>
  </titleInfo>
  <name type="personal">
      <namePart>Prett, Alasdair</namePart>
     <role>
       <roleTerm>lyricist</roleTerm>
     </role>
  </name>
  <typeOfResource>text</typeOfResource>
</relatedItem>

<relatedItem type="constituent">
  <titleInfo>
   <title>Who Am I</title>
  </titleInfo>
  <name type="personal">
      <namePart>Chua, Terence</namePart>
     <role>
       <roleTerm>lyricist</roleTerm>
     </role>
  </name>
  <typeOfResource>text</typeOfResource>
</relatedItem>

<relatedItem type="constituent">
  <titleInfo>
   <title>Doctor Doctor</title>
  </titleInfo>
  <name type="personal">
      <namePart>Bristow, Paul</namePart>
     <role>
       <roleTerm>lyricist</roleTerm>
     </role>
  </name>
  <typeOfResource>text</typeOfResource>
</relatedItem>

<relatedItem type="constituent">
  <titleInfo>
   <title>Timelords and Travellers</title>
  </titleInfo>
  <name type="personal">
      <namePart>Dean, Lawrence</namePart>
     <role>
       <roleTerm>lyricist</roleTerm>
     </role>
  </name>
  <name type="personal">
      <namePart>Dean, Deborah</namePart>
     <role>
       <roleTerm>lyricist</roleTerm>
     </role>
  </name>
  <typeOfResource>text</typeOfResource>
</relatedItem>

<relatedItem type="constituent">
  <titleInfo>
   <title>Captain Jack and the Doctor</title>
  </titleInfo>
  <name type="personal">
      <namePart>James, Rhodri</namePart>
     <role>
       <roleTerm>lyricist</roleTerm>
     </role>
  </name>
  <typeOfResource>text</typeOfResource>
</relatedItem>

<relatedItem type="constituent">
  <titleInfo>
   <title>El Doctîr</title>
  </titleInfo>
  <name type="personal">
      <namePart>Freeman, Nancy L.</namePart>
     <role>
       <roleTerm>lyricist</roleTerm>
     </role>
  </name>
  <typeOfResource>text</typeOfResource>
</relatedItem>

<relatedItem type="constituent">
  <titleInfo>
   <title>A Companions' Christmas</title>
  </titleInfo>
  <name type="personal">
      <namePart>Chua, Terence</namePart>
     <role>
       <roleTerm>lyricist</roleTerm>
     </role>
  </name>
  <typeOfResource>text</typeOfResource>
</relatedItem>

<relatedItem type="constituent">
  <titleInfo>
   <title>More Like the Tardis</title>
  </titleInfo>
  <name type="personal">
      <namePart>Williams, Tricia</namePart>
     <role>
       <roleTerm>lyricist</roleTerm>
     </role>
  </name>
  <typeOfResource>text</typeOfResource>
</relatedItem>

<relatedItem type="constituent">
  <titleInfo>
   <title>Song for Companions</title>
  </titleInfo>
  <name type="personal">
      <namePart>Titman, Nat</namePart>
     <role>
       <roleTerm>lyricist</roleTerm>
     </role>
  </name>
  <typeOfResource>text</typeOfResource>
</relatedItem>

<relatedItem type="constituent">
  <titleInfo>
   <title>Leap of Faith</title>
  </titleInfo>
  <name type="personal">
      <namePart>Chua, Terence</namePart>
     <role>
       <roleTerm>lyricist</roleTerm>
     </role>
  </name>
  <typeOfResource>text</typeOfResource>
</relatedItem>

<relatedItem type="constituent">
  <titleInfo>
   <title>The Bat and the Crow</title>
  </titleInfo>
  <name type="personal">
      <namePart>Goss, Adam</namePart>
     <role>
       <roleTerm>lyricist</roleTerm>
     </role>
  </name>
  <typeOfResource>text</typeOfResource>
</relatedItem>

<relatedItem type="constituent">
  <titleInfo>
   <title>Enigma in Black</title>
  </titleInfo>
  <name type="personal">
      <namePart>Graham, Jessica</namePart>
     <role>
       <roleTerm>lyricist</roleTerm>
     </role>
  </name>
  <name type="personal">
      <namePart>Prett, Alasdair</namePart>
     <role>
       <roleTerm>lyricist</roleTerm>
     </role>
  </name>
  <typeOfResource>text</typeOfResource>
</relatedItem>

<relatedItem type="constituent">
  <titleInfo>
   <title>Waiting Game</title>
  </titleInfo>
  <name type="personal">
      <namePart>Dennis, Miki</namePart>
     <role>
       <roleTerm>lyricist</roleTerm>
     </role>
  </name>
  <typeOfResource>text</typeOfResource>
</relatedItem>

<relatedItem type="constituent">
  <titleInfo>
   <title>Amber Wine</title>
  </titleInfo>
  <name type="personal">
      <namePart>Honisch, Juliane</namePart>
     <role>
       <roleTerm>lyricist</roleTerm>
     </role>
  </name>
  <typeOfResource>text</typeOfResource>
</relatedItem>

<relatedItem type="constituent">
  <titleInfo>
   <title>Poor Old Prince</title>
  </titleInfo>
  <name type="personal">
      <namePart>Dragster</namePart>
     <role>
       <roleTerm>lyricist</roleTerm>
     </role>
  </name>
  <typeOfResource>text</typeOfResource>
</relatedItem>

<relatedItem type="constituent">
  <titleInfo>
   <title>Dragon Queen</title>
  </titleInfo>
  <name type="personal">
      <namePart>Sterry, Kathy</namePart>
     <role>
       <roleTerm>lyricist</roleTerm>
     </role>
  </name>
  <typeOfResource>text</typeOfResource>
</relatedItem>

<relatedItem type="constituent">
  <titleInfo>
   <title>Flash of the Flame</title>
  </titleInfo>
  <name type="personal">
      <namePart>Sterry, Kathy</namePart>
     <role>
       <roleTerm>lyricist</roleTerm>
     </role>
  </name>
  <typeOfResource>text</typeOfResource>
</relatedItem>

<relatedItem type="constituent">
  <titleInfo>
   <title>Song of the Happy Dragon</title>
  </titleInfo>
  <name type="personal">
      <namePart>Sterry, Kathy</namePart>
     <role>
       <roleTerm>lyricist</roleTerm>
     </role>
  </name>
  <typeOfResource>text</typeOfResource>
</relatedItem>

<relatedItem type="constituent">
  <titleInfo>
   <title>What Kitty Did Next</title>
  </titleInfo>
  <name type="personal">
      <namePart>Soley Barton, Kate</namePart>
     <role>
       <roleTerm>lyricist</roleTerm>
     </role>
  </name>
  <typeOfResource>text</typeOfResource>
</relatedItem>

<relatedItem type="constituent">
  <titleInfo>
   <title>Parental Advisory</title>
  </titleInfo>
  <name type="personal">
      <namePart>Richards, Mike</namePart>
     <role>
       <roleTerm>lyricist</roleTerm>
     </role>
  </name>
  <typeOfResource>text</typeOfResource>
</relatedItem>

<relatedItem type="constituent">
  <titleInfo>
   <title>Cthulhu-Doo, Where Are You?</title>
  </titleInfo>
  <name type="personal">
      <namePart>Goss, Adam R.</namePart>
     <role>
       <roleTerm>lyricist</roleTerm>
     </role>
  </name>
  <typeOfResource>text</typeOfResource>
</relatedItem>

<relatedItem type="constituent">
  <titleInfo>
   <title>Or Should It Be Ghoul?</title>
  </titleInfo>
  <name type="personal">
      <namePart>Biddle, Brian</namePart>
     <role>
       <roleTerm>lyricist</roleTerm>
     </role>
  </name>
  <typeOfResource>text</typeOfResource>
</relatedItem>

<relatedItem type="constituent">
  <titleInfo>
   <title>Potentials</title>
  </titleInfo>
  <name type="personal">
      <namePart>Nyrond, Zander</namePart>
     <role>
       <roleTerm>lyricist</roleTerm>
     </role>
  </name>
  <typeOfResource>text</typeOfResource>
</relatedItem>

<relatedItem type="constituent">
  <titleInfo>
   <title>My Christmas Wish</title>
   <subTitle>The Hobbit-Boy Song</subTitle>
  </titleInfo>
  <name type="personal">
      <namePart>Chilton, Julie</namePart>
     <role>
       <roleTerm>lyricist</roleTerm>
     </role>
  </name>
  <typeOfResource>text</typeOfResource>
</relatedItem>

<relatedItem type="constituent">
  <titleInfo>
   <title>Beauty and the Beast</title>
  </titleInfo>
  <name type="personal">
      <namePart>Bristow, Paul</namePart>
     <role>
       <roleTerm>lyricist</roleTerm>
     </role>
  </name>
  <typeOfResource>text</typeOfResource>
</relatedItem>

<relatedItem type="constituent">
  <titleInfo>
   <title>It's Your Party</title>
  </titleInfo>
  <name type="personal">
      <namePart>Biddle, Brian</namePart>
     <role>
       <roleTerm>lyricist</roleTerm>
     </role>
  </name>
  <typeOfResource>text</typeOfResource>
</relatedItem>

<relatedItem type="constituent">
  <titleInfo>
   <title>May the Turtle Be Unbroken</title>
  </titleInfo>
  <name type="personal">
      <namePart>McGath, Gary</namePart>
     <role>
       <roleTerm>lyricist</roleTerm>
     </role>
  </name>
  <relatedItem type="preceding">
      <titleInfo>
       <title>Will the Circle Be Unbroken</title>
      </titleInfo>
      <note>Tune suggested or parodied</note>
  </relatedItem>
  <typeOfResource>text</typeOfResource>
</relatedItem>

<relatedItem type="constituent">
  <titleInfo>
   <title>Uberwald Lament</title>
  </titleInfo>
  <name type="personal">
      <namePart>Prett, Alasdair</namePart>
     <role>
       <roleTerm>lyricist</roleTerm>
     </role>
  </name>
  <typeOfResource>text</typeOfResource>
</relatedItem>

<relatedItem type="constituent">
  <titleInfo>
   <title>Last Journey</title>
  </titleInfo>
  <name type="personal">
      <namePart>Chilton, Julie</namePart>
     <role>
       <roleTerm>lyricist</roleTerm>
     </role>
  </name>
  <typeOfResource>text</typeOfResource>
</relatedItem>

<relatedItem type="constituent">
  <titleInfo>
   <title>Pale Rider / Pale Horse</title>
  </titleInfo>
  <name type="personal">
      <namePart>Dennis, Miki</namePart>
     <role>
       <roleTerm>lyricist</roleTerm>
     </role>
  </name>
  <typeOfResource>text</typeOfResource>
</relatedItem>

<relatedItem type="constituent">
  <titleInfo>
   <title>Poor Myrtle</title>
  </titleInfo>
  <name type="personal">
      <namePart>Honisch, Juliane</namePart>
     <role>
       <roleTerm>lyricist</roleTerm>
     </role>
  </name>
  <typeOfResource>text</typeOfResource>
</relatedItem>

<relatedItem type="constituent">
  <titleInfo>
   <title>On the Other Side</title>
  </titleInfo>
  <name type="personal">
      <namePart>Prett, Alasdair</namePart>
     <role>
       <roleTerm>lyricist</roleTerm>
     </role>
  </name>
  <typeOfResource>text</typeOfResource>
</relatedItem>

<relatedItem type="constituent">
  <titleInfo>
   <title>The Watchman's Lament</title>
  </titleInfo>
  <name type="personal">
      <namePart>Nanson, Tom</namePart>
     <role>
       <roleTerm>lyricist</roleTerm>
     </role>
  </name>
  <typeOfResource>text</typeOfResource>
</relatedItem>

<relatedItem type="constituent">
  <titleInfo>
   <title>Only Children and Fools</title>
  </titleInfo>
  <name type="personal">
      <namePart>Nanson, Tom</namePart>
     <role>
       <roleTerm>lyricist</roleTerm>
     </role>
  </name>
  <typeOfResource>text</typeOfResource>
</relatedItem>

<relatedItem type="constituent">
  <titleInfo>
   <title>Hurl Blue Fire</title>
  </titleInfo>
  <name type="personal">
      <namePart>Nanson, Tom</namePart>
     <role>
       <roleTerm>lyricist</roleTerm>
     </role>
  </name>
  <typeOfResource>text</typeOfResource>
</relatedItem>

<relatedItem type="constituent">
  <titleInfo>
   <title>Dawn</title>
  </titleInfo>
  <name type="personal">
      <namePart>James, Rhodri</namePart>
     <role>
       <roleTerm>lyricist</roleTerm>
     </role>
  </name>
  <typeOfResource>text</typeOfResource>
</relatedItem>


</mods>
