<?xml version="1.0" encoding="UTF-8"?>
<?xml-stylesheet href="stylesheets/modshtml.xsl" type="text/xsl" ?>
<mods version="3.1" xmlns="http://www.loc.gov/mods/v3" ID="unchartedstars">
<recordInfo>
<recordCreationDate>2009-12-30</recordCreationDate>
<recordChangeDate>2009-12-30</recordChangeDate>
<!-- If you modify this file, please update the recordChangeDate element -->
</recordInfo>
<titleInfo>
<title>Uncharted Stars</title>
<subTitle>Lyric &amp; Chord Book</subTitle>
</titleInfo>
<originInfo>
<place>
  <placeTerm type="text">Berkeley, California</placeTerm>
</place>
<publisher>Unlikely Publications</publisher>
<dateIssued>1993</dateIssued>
</originInfo>
<language>
<languageTerm type="code" authority="iso639-2b">eng</languageTerm>
</language>
<physicalDescription>
<form authority="marcform">print</form>
</physicalDescription>
<name type="personal">
<namePart>McQuillin, Cynthia</namePart>
<role>
<roleTerm>editor</roleTerm>
<roleTerm>author</roleTerm>
</role>
</name>
<name type="personal">
<namePart>Simpson, Don</namePart>
<role>
<roleTerm>illustrator</roleTerm>
</role>
</name>

<relatedItem type="constituent">
  <titleInfo>
   <title>Hunter of Worlds</title>
  </titleInfo>
  <name type="personal">
      <namePart>McQuillin, Cynthia</namePart>
     <role>
       <roleTerm>lyricist</roleTerm>
     </role>
     <role>
       <roleTerm>composer</roleTerm>
     </role>
  </name>
  <typeOfResource>text</typeOfResource>
</relatedItem>

<relatedItem type="constituent">
  <titleInfo>
   <title>Earthers Are Easy</title>
  </titleInfo>
  <name type="personal">
      <namePart>McQuillin, Cynthia</namePart>
     <role>
       <roleTerm>lyricist</roleTerm>
     </role>
     <role>
       <roleTerm>composer</roleTerm>
     </role>
  </name>
  <typeOfResource>text</typeOfResource>
</relatedItem>

<relatedItem type="constituent">
  <titleInfo>
   <title>Tribute to Lost Cities</title>
   <subTitle>(Fight and Die!)</subTitle>
  </titleInfo>
  <name type="personal">
      <namePart>McQuillin, Cynthia</namePart>
     <role>
       <roleTerm>lyricist</roleTerm>
     </role>
     <role>
       <roleTerm>composer</roleTerm>
     </role>
  </name>
  <typeOfResource>text</typeOfResource>
</relatedItem>

<relatedItem type="constituent">
  <titleInfo>
   <title>Castaway</title>
  </titleInfo>
  <name type="personal">
      <namePart>McQuillin, Cynthia</namePart>
     <role>
       <roleTerm>lyricist</roleTerm>
     </role>
     <role>
       <roleTerm>composer</roleTerm>
     </role>
  </name>
  <typeOfResource>text</typeOfResource>
</relatedItem>

<relatedItem type="constituent">
  <titleInfo>
   <title>Silver Ships</title>
  </titleInfo>
  <name type="personal">
      <namePart>McQuillin, Cynthia</namePart>
     <role>
       <roleTerm>lyricist</roleTerm>
     </role>
     <role>
       <roleTerm>composer</roleTerm>
     </role>
  </name>
  <typeOfResource>text</typeOfResource>
</relatedItem>

<relatedItem type="constituent">
  <titleInfo>
   <title>Samaritan</title>
  </titleInfo>
  <name type="personal">
      <namePart>McQuillin, Cynthia</namePart>
     <role>
       <roleTerm>lyricist</roleTerm>
     </role>
     <role>
       <roleTerm>composer</roleTerm>
     </role>
  </name>
  <typeOfResource>text</typeOfResource>
</relatedItem>

<relatedItem type="constituent">
  <titleInfo>
   <title>Sleepers</title>
  </titleInfo>
  <name type="personal">
      <namePart>McQuillin, Cynthia</namePart>
     <role>
       <roleTerm>lyricist</roleTerm>
     </role>
     <role>
       <roleTerm>composer</roleTerm>
     </role>
  </name>
  <typeOfResource>text</typeOfResource>
</relatedItem>

<relatedItem type="constituent">
  <titleInfo>
   <title>When Legends Die</title>
  </titleInfo>
  <name type="personal">
      <namePart>McQuillin, Cynthia</namePart>
     <role>
       <roleTerm>lyricist</roleTerm>
     </role>
     <role>
       <roleTerm>composer</roleTerm>
     </role>
  </name>
  <typeOfResource>text</typeOfResource>
</relatedItem>

<relatedItem type="constituent">
  <titleInfo>
   <title>Star Bound Spirit</title>
  </titleInfo>
  <name type="personal">
      <namePart>McQuillin, Cynthia</namePart>
     <role>
       <roleTerm>lyricist</roleTerm>
     </role>
     <role>
       <roleTerm>composer</roleTerm>
     </role>
  </name>
  <typeOfResource>text</typeOfResource>
</relatedItem>

<relatedItem type="constituent">
  <titleInfo>
   <title>Star Merchants</title>
  </titleInfo>
  <name type="personal">
      <namePart>McQuillin, Cynthia</namePart>
     <role>
       <roleTerm>lyricist</roleTerm>
     </role>
     <role>
       <roleTerm>composer</roleTerm>
     </role>
  </name>
  <typeOfResource>text</typeOfResource>
</relatedItem>

<relatedItem type="constituent">
  <titleInfo>
   <title>Long Way Home</title>
  </titleInfo>
  <name type="personal">
      <namePart>McQuillin, Cynthia</namePart>
     <role>
       <roleTerm>lyricist</roleTerm>
     </role>
     <role>
       <roleTerm>composer</roleTerm>
     </role>
  </name>
  <typeOfResource>text</typeOfResource>
</relatedItem>

<relatedItem type="constituent">
  <titleInfo>
   <title>Journeys</title>
  </titleInfo>
  <name type="personal">
      <namePart>McQuillin, Cynthia</namePart>
     <role>
       <roleTerm>lyricist</roleTerm>
     </role>
     <role>
       <roleTerm>composer</roleTerm>
     </role>
  </name>
  <typeOfResource>text</typeOfResource>
</relatedItem>

<relatedItem type="constituent">
  <titleInfo>
   <title>When Angels Fall</title>
  </titleInfo>
  <name type="personal">
      <namePart>McQuillin, Cynthia</namePart>
     <role>
       <roleTerm>lyricist</roleTerm>
     </role>
     <role>
       <roleTerm>composer</roleTerm>
     </role>
  </name>
  <typeOfResource>text</typeOfResource>
</relatedItem>

<relatedItem type="constituent">
  <titleInfo>
   <title>Luck Is a Jade</title>
  </titleInfo>
  <name type="personal">
      <namePart>McQuillin, Cynthia</namePart>
     <role>
       <roleTerm>lyricist</roleTerm>
     </role>
     <role>
       <roleTerm>composer</roleTerm>
     </role>
  </name>
  <typeOfResource>text</typeOfResource>
</relatedItem>

<relatedItem type="constituent">
  <titleInfo>
   <title>Uncharted Stars</title>
  </titleInfo>
  <name type="personal">
      <namePart>McQuillin, Cynthia</namePart>
     <role>
       <roleTerm>lyricist</roleTerm>
     </role>
     <role>
       <roleTerm>composer</roleTerm>
     </role>
  </name>
  <typeOfResource>text</typeOfResource>
</relatedItem>

<relatedItem type="constituent">
  <titleInfo>
   <title>I Only Dream of Going Home</title>
  </titleInfo>
  <name type="personal">
      <namePart>McQuillin, Cynthia</namePart>
     <role>
       <roleTerm>lyricist</roleTerm>
     </role>
     <role>
       <roleTerm>composer</roleTerm>
     </role>
  </name>
  <typeOfResource>text</typeOfResource>
</relatedItem>

<relatedItem type="constituent">
  <titleInfo>
   <title>Ghost Ship</title>
  </titleInfo>
  <name type="personal">
      <namePart>McQuillin, Cynthia</namePart>
     <role>
       <roleTerm>lyricist</roleTerm>
     </role>
     <role>
       <roleTerm>composer</roleTerm>
     </role>
  </name>
  <typeOfResource>text</typeOfResource>
</relatedItem>

<relatedItem type="constituent">
  <titleInfo>
   <title>Survivor</title>
  </titleInfo>
  <name type="personal">
      <namePart>McQuillin, Cynthia</namePart>
     <role>
       <roleTerm>lyricist</roleTerm>
     </role>
     <role>
       <roleTerm>composer</roleTerm>
     </role>
  </name>
  <typeOfResource>text</typeOfResource>
</relatedItem>

<relatedItem type="constituent">
  <titleInfo>
   <title>Space Station Annie</title>
  </titleInfo>
  <name type="personal">
      <namePart>McQuillin, Cynthia</namePart>
     <role>
       <roleTerm>lyricist</roleTerm>
     </role>
     <role>
       <roleTerm>composer</roleTerm>
     </role>
  </name>
  <typeOfResource>text</typeOfResource>
</relatedItem>

<relatedItem type="constituent">
  <titleInfo>
   <title>Illusion Maker</title>
  </titleInfo>
  <name type="personal">
      <namePart>McQuillin, Cynthia</namePart>
     <role>
       <roleTerm>lyricist</roleTerm>
     </role>
     <role>
       <roleTerm>composer</roleTerm>
     </role>
  </name>
  <typeOfResource>text</typeOfResource>
</relatedItem>

<relatedItem type="constituent">
  <titleInfo>
   <title>Cybernetic Necromancy</title>
  </titleInfo>
  <name type="personal">
      <namePart>McQuillin, Cynthia</namePart>
     <role>
       <roleTerm>lyricist</roleTerm>
     </role>
     <role>
       <roleTerm>composer</roleTerm>
     </role>
  </name>
  <typeOfResource>text</typeOfResource>
</relatedItem>

<relatedItem type="constituent">
  <titleInfo>
   <title>Christine's Song</title>
  </titleInfo>
  <name type="personal">
      <namePart>McQuillin, Cynthia</namePart>
     <role>
       <roleTerm>lyricist</roleTerm>
     </role>
     <role>
       <roleTerm>composer</roleTerm>
     </role>
  </name>
  <typeOfResource>text</typeOfResource>
</relatedItem>

<relatedItem type="constituent">
  <titleInfo>
   <title>Soft Rains</title>
  </titleInfo>
  <name type="personal">
      <namePart>McQuillin, Cynthia</namePart>
     <role>
       <roleTerm>lyricist</roleTerm>
     </role>
     <role>
       <roleTerm>composer</roleTerm>
     </role>
  </name>
  <typeOfResource>text</typeOfResource>
</relatedItem>


</mods>
